__init__.py
felisaparser/__init__.py
felisaparser/felisaparser.py
felisaparser-1.0.4.dist-info/LICENSE.txt
felisaparser-1.0.4.dist-info/METADATA
felisaparser-1.0.4.dist-info/WHEEL
felisaparser-1.0.4.dist-info/top_level.txt
felisaparser-1.0.4.dist-info/RECORD
