Metadata-Version: 2.1
Name: felisaparser
Version: 1.0.4
Summary: This package contains a function to directly parse a excel file into a csv file
Home-page: https://github.com/daviddelriod/felisaparser
Author: Adrián Martínez, David Del Río
License: GPL-2.0
Keywords: xlsx parser
License-File: LICENSE.txt
Requires-Dist: pandas
